{"en-us_guide_faq.md":"40484966","en-us_guide_changelog.md":"8c48f59c","en-us_guide_datasource.md":"4703c552","en-us_guide_feedback.md":"6037f6b6","en-us_guide_hot-key.md":"665c1205","en-us_guide_environment.md":"000fb463","en-us_guide_i18n.md":"00fe8294","en-us_guide_figure.md":"15eed7d9","guide_faq.md":"13fe6a35","guide_hot-key.md":"9a1a003b","guide_datasource.md":"68140a9c","en-us_guide_what-is-klinechart.md":"06b40029","en-us_sponsor.md":"88a012aa","guide_i18n.md":"0f48bc44","en-us_guide_overlay.md":"0b9bd528","en-us_guide_getting-started.md":"dff5d1d7","en-us_guide_v8-to-v9.md":"47153d1f","en-us_guide_chart-api.md":"22aa2e1c","guide_changelog.md":"58b71787","en-us_index.md":"8beee9e9","en-us_guide_indicator.md":"475a2720","guide_feedback.md":"f1094dcd","guide_getting-started.md":"cfdac1e7","guide_environment.md":"49601d6a","en-us_guide_styles.md":"0377de95","guide_indicator.md":"9d54fdfc","sponsor.md":"047aba98","guide_what-is-klinechart.md":"8e7d402c","guide_figure.md":"c3dc7c9e","guide_overlay.md":"08bc3195","guide_v8-to-v9.md":"5ff337d1","index.md":"ca6f30e1","en-us_guide_instance-api.md":"4818a534","guide_chart-api.md":"68a24168","guide_styles.md":"dab028fe","guide_instance-api.md":"2c1cae5a"}
